concert_launcher/__init__.py
concert_launcher/concert_launcher.bash
concert_launcher/config.py
concert_launcher/executor.py
concert_launcher/main.py
concert_launcher/monitoring_session.py
concert_launcher/print_utils.py
concert_launcher/remote.py
concert_launcher/resources/concert_launcher_print_ps_tree.py
concert_launcher/resources/concert_launcher_wrapper.bash
concert_launcher-0.1.1.dist-info/METADATA
concert_launcher-0.1.1.dist-info/WHEEL
concert_launcher-0.1.1.dist-info/entry_points.txt
concert_launcher-0.1.1.dist-info/top_level.txt
concert_launcher-0.1.1.dist-info/RECORD
