Metadata-Version: 2.1
Name: concert-launcher
Version: 0.1.1
Summary: A minimalistic tool to automate remote process launching with dependencies
Home-page: https://none
Author: Arturo Laurenzi
Author-email: arturo.laurenzi@iit.it
License: UNKNOWN
Project-URL: Bug Tracker, https://none
Platform: UNKNOWN
Classifier: Programming Language :: Python :: 3
Classifier: License :: OSI Approved :: MIT License
Classifier: Operating System :: OS Independent
Requires-Python: >=3.6
Requires-Dist: argcomplete
Requires-Dist: parse
Requires-Dist: pyyaml
Requires-Dist: asyncssh
